LICENSE
MANIFEST.in
README.rst
setup.py
entur_api/Activity.py
entur_api/EnturGraphQL.py
entur_api/EnturJourneyPlanner.py
entur_api/EnturJourneyPlannerUtils.py
entur_api/EnturVehicles.py
entur_api/GeoCoder.py
entur_api/__init__.py
entur_api/cache_vm.py
entur_api/enturcommon.py
entur_api/siri.py
entur_api.egg-info/PKG-INFO
entur_api.egg-info/SOURCES.txt
entur_api.egg-info/dependency_links.txt
entur_api.egg-info/requires.txt
entur_api.egg-info/top_level.txt
entur_api/tests/__init__.py
entur_api/tests/test_JourneyPlanner.py
entur_api/tests/test_find_vehicle_activity.py
entur_api/tests/test_geocoder.py
entur_api/tests/test_requests.py
entur_api/tests/test_siri.py