Metadata-Version: 2.1
Name: entur-api
Version: 1.0
Summary: Tools to work with enturs API
Home-page: https://github.com/datagutten/entur-api
Author: Anders Birkenes
Author-email: datagutten@datagutten.net
License: GPL
Platform: UNKNOWN
Classifier: Environment :: Web Environment
Classifier: Intended Audience :: Developers
Classifier: License :: OSI Approved :: GNU General Public License v3 or later (GPLv3+)
Classifier: Operating System :: OS Independent
Classifier: Programming Language :: Python
Classifier: Programming Language :: Python :: 3.5
Classifier: Programming Language :: Python :: 3.6
Classifier: Topic :: Internet :: WWW/HTTP
Classifier: Topic :: Internet :: WWW/HTTP :: Dynamic Content
